<?xml version="1.0"?>
<!DOCTYPE hibernate-mapping PUBLIC "-//Hibernate/Hibernate Mapping DTD 3.0//EN"
"http://hibernate.sourceforge.net/hibernate-mapping-3.0.dtd">
<!-- Generated 10-12-2012 11:39:02 AM by Hibernate Tools 3.2.1.GA -->
<hibernate-mapping>
    <class name="tablas.RolesXUsuarios" table="roles_x_usuarios" catalog="papergeneratordb">
        <composite-id name="id" class="tablas.RolesXUsuariosId">
            <key-property name="idRol" type="int">
                <column name="id_rol" />
            </key-property>
            <key-property name="correo" type="string">
                <column name="correo" length="50" />
            </key-property>
        </composite-id>
    </class>
</hibernate-mapping>
